.hgignore
.hgtags
CHANGELOG.txt
LICENSE.txt
MANIFEST.in
README.rst
setup.py
django_shoogie.egg-info/PKG-INFO
django_shoogie.egg-info/SOURCES.txt
django_shoogie.egg-info/dependency_links.txt
django_shoogie.egg-info/requires.txt
django_shoogie.egg-info/top_level.txt
shoogie/__init__.py
shoogie/admin.py
shoogie/log_handler.py
shoogie/logger.py
shoogie/middleware.py
shoogie/models.py
shoogie/utils.py
shoogie/views.py