Metadata-Version: 1.1
Name: django-shoogie
Version: 0.7
Summary: Log server errors to database
Home-page: http://bitbucket.org/altaurog/django-shoogie
Author: Aryeh Leib Taurog
Author-email: python@aryehleib.com
License: MIT
Platform: UNKNOWN
Classifier: Programming Language :: Python
Classifier: Programming Language :: Python :: 2.6
Classifier: Development Status :: 5 - Production/Stable
Classifier: License :: OSI Approved :: MIT License
Classifier: Operating System :: OS Independent
Classifier: Intended Audience :: Developers
Classifier: Environment :: Web Environment
Classifier: Topic :: Software Development :: Libraries :: Python Modules
Classifier: Topic :: Internet :: WWW/HTTP
Classifier: Topic :: System :: Logging
Classifier: Topic :: Database
Classifier: Framework :: Django
